dequest/__init__.py
dequest/circuit_breaker.py
dequest/config.py
dequest/exceptions.py
dequest/http.py
dequest/parameter_types.py
dequest/utils.py
dequest/cache/__init__.py
dequest/cache/_cache.py
dequest/cache/cache_driver_factory.py
dequest/cache/cache_drivers/__init__.py
dequest/cache/cache_drivers/cache_driver.py
dequest/cache/cache_drivers/django_driver.py
dequest/cache/cache_drivers/local_memory_driver.py
dequest/cache/cache_drivers/redis_driver.py
dequest/clients/__init__.py
dequest/clients/_async.py
dequest/clients/_sync.py
tests/__init__.py
tests/test_async_client.py
tests/test_async_loop_manager.py
tests/test_cache.py
tests/test_config.py
tests/test_http.py
tests/test_in_memory_cache.py
tests/test_perform_request.py
tests/test_sync_client.py
tests/test_utils.py
tests/test_xml_to_dto.py
dequest-0.5.0.dist-info/METADATA
dequest-0.5.0.dist-info/WHEEL
dequest-0.5.0.dist-info/top_level.txt
dequest-0.5.0.dist-info/RECORD
