Metadata-Version: 2.4
Name: dequest
Version: 0.5.0
Summary: Declarative rest client
Home-page: https://github.com/birddevelper/dequest
Download-URL: https://github.com/birddevelper/dequest
Author: R.E
License: GNU
Keywords: request,declarative,api,rest,rest client
Requires-Dist: redis>=5.2.1
Requires-Dist: defusedxml>=0.7.1
Requires-Dist: httpx>=0.28.1
Dynamic: author
Dynamic: description
Dynamic: description-content-type
Dynamic: download-url
Dynamic: home-page
Dynamic: keywords
Dynamic: license
Dynamic: requires-dist
Dynamic: summary
